artpop/__init__.py
artpop/filters.py
artpop/log.py
artpop/source.py
artpop/util.py
artpop/visualization.py
artpop/viz.py
artpop/data/feh_m1.00_vvcrit0.4_LSST_10gyr_test_iso.pkl
artpop/data/filter_properties.fits
artpop/data/filter_properties.pkl
artpop/data/mist_filter_names.pkl
artpop/data/phot_system_lookup.pkl
artpop/data/zeropoints.txt
artpop/data/filters/mist_filter_names.pkl
artpop/data/filters/phot_system_lookup.pkl
artpop/data/filters/zeropoints.txt
artpop/data/filters/CFHTugriz/CFHT_g.csv
artpop/data/filters/CFHTugriz/CFHT_i_new.csv
artpop/data/filters/CFHTugriz/CFHT_i_old.csv
artpop/data/filters/CFHTugriz/CFHT_r.csv
artpop/data/filters/CFHTugriz/CFHT_u.csv
artpop/data/filters/CFHTugriz/CFHT_z.csv
artpop/data/filters/DECam/DECam_Y.csv
artpop/data/filters/DECam/DECam_g.csv
artpop/data/filters/DECam/DECam_i.csv
artpop/data/filters/DECam/DECam_r.csv
artpop/data/filters/DECam/DECam_u.csv
artpop/data/filters/DECam/DECam_z.csv
artpop/data/filters/HSC/hsc_g.csv
artpop/data/filters/HSC/hsc_i.csv
artpop/data/filters/HSC/hsc_nb816.csv
artpop/data/filters/HSC/hsc_nb921.csv
artpop/data/filters/HSC/hsc_r.csv
artpop/data/filters/HSC/hsc_y.csv
artpop/data/filters/HSC/hsc_z.csv
artpop/data/filters/HST_ACSWF/ACS_WFC_F435W.csv
artpop/data/filters/HST_ACSWF/ACS_WFC_F475W.csv
artpop/data/filters/HST_ACSWF/ACS_WFC_F502N.csv
artpop/data/filters/HST_ACSWF/ACS_WFC_F550M.csv
artpop/data/filters/HST_ACSWF/ACS_WFC_F555W.csv
artpop/data/filters/HST_ACSWF/ACS_WFC_F606W.csv
artpop/data/filters/HST_ACSWF/ACS_WFC_F625W.csv
artpop/data/filters/HST_ACSWF/ACS_WFC_F658N.csv
artpop/data/filters/HST_ACSWF/ACS_WFC_F660N.csv
artpop/data/filters/HST_ACSWF/ACS_WFC_F775W.csv
artpop/data/filters/HST_ACSWF/ACS_WFC_F814W.csv
artpop/data/filters/HST_ACSWF/ACS_WFC_F850LP.csv
artpop/data/filters/HST_WFC3/WFC3_IR_F098M.csv
artpop/data/filters/HST_WFC3/WFC3_IR_F105W.csv
artpop/data/filters/HST_WFC3/WFC3_IR_F110W.csv
artpop/data/filters/HST_WFC3/WFC3_IR_F125W.csv
artpop-0.1.1.dist-info/LICENSE
artpop-0.1.1.dist-info/METADATA
artpop-0.1.1.dist-info/WHEEL
artpop-0.1.1.dist-info/top_level.txt
artpop-0.1.1.dist-info/RECORD
