Metadata-Version: 2.1
Name: artpop
Version: 0.1.1
Summary: Building artificial galaxies one star at a time
Home-page: https://github.com/ArtificialStellarPopulations/ArtPop
Author: Johnny Greco & Shany Danieli
Author-email: artpopcode@gmail.com
License: UNKNOWN
Platform: UNKNOWN
Classifier: Programming Language :: Python :: 3
Classifier: License :: OSI Approved :: MIT License
Classifier: Intended Audience :: Science/Research
Classifier: Operating System :: OS Independent
Classifier: Topic :: Scientific/Engineering :: Astronomy
Requires-Python: >=3.6
License-File: LICENSE
Requires-Dist: numpy (>=1.17)
Requires-Dist: scipy (>=1)
Requires-Dist: astropy (>=4)
Requires-Dist: matplotlib (>=3)
Requires-Dist: fast-histogram (>=0.9)
Requires-Dist: requests
